Metadata-Version: 1.0
Name: thom02
Version: 0.2
Summary: Gaussian distributions
Home-page: UNKNOWN
Author: Nguyen Huong Thom
Author-email: nguyenhuongthom@gmail.com
License: UNKNOWN
Platform: UNKNOWN
